{
  "users": [
    {
      "id": 1,
      "usuario": "chicho",
      "password": "chicho01",
      "rol": "admin"
    },
    {
      "id": 2,
      "usuario": "rosalba",
      "password": "rosalba01",
      "rol": "operador"
    }
  ],
  "clientes": [
    {
      "id": 1,
      "nombre": "jovanni",
      "apel1": "segura",
      "apell2": "isla",
      "identidad": 74072310643
    },
    {
      "id": 2,
      "nombre": "dayami",
      "apel1": "lopez",
      "apell2": "fournier",
      "identidad": 75110810643
    }
  ]
}